AUTHORS
CHANGELOG.txt
DESCRIPTION
LICENSE
MANIFEST.in
README.rst
setup.py
cmsplugin_blog_categories/__init__.py
cmsplugin_blog_categories/admin.py
cmsplugin_blog_categories/cms_app.py
cmsplugin_blog_categories/cms_plugins.py
cmsplugin_blog_categories/models.py
cmsplugin_blog_categories/simple_translate.py
cmsplugin_blog_categories/urls.py
cmsplugin_blog_categories/views.py
cmsplugin_blog_categories.egg-info/PKG-INFO
cmsplugin_blog_categories.egg-info/SOURCES.txt
cmsplugin_blog_categories.egg-info/dependency_links.txt
cmsplugin_blog_categories.egg-info/top_level.txt
cmsplugin_blog_categories/migrations/0001_initial.py
cmsplugin_blog_categories/migrations/0002_auto__add_categoryplugin.py
cmsplugin_blog_categories/migrations/0003_auto__del_field_categoryplugin_category.py
cmsplugin_blog_categories/migrations/0004_auto__del_unique_entrycategory_category_entry.py
cmsplugin_blog_categories/migrations/0005_auto__add_field_categoryplugin_template_argument.py
cmsplugin_blog_categories/migrations/0006_auto__add_field_category_parent.py
cmsplugin_blog_categories/migrations/__init__.py
cmsplugin_blog_categories/templates/cmsplugin_blog_categories/category_links_snippet.html
cmsplugin_blog_categories/templates/cmsplugin_blog_categories/category_plugin.html
cmsplugin_blog_categories/templates/cmsplugin_blog_categories/entry_archive_category.html
cmsplugin_blog_categories/templates/cmsplugin_blog_categories/partials/entry_list.html
cmsplugin_blog_categories/templatetags/__init__.py
cmsplugin_blog_categories/templatetags/cmsplugin_blog_categories_tags.py
cmsplugin_blog_categories/tests/__init__.py
cmsplugin_blog_categories/tests/cmsplugin_tests.py
cmsplugin_blog_categories/tests/factories.py
cmsplugin_blog_categories/tests/models_tests.py
cmsplugin_blog_categories/tests/runtests.py
cmsplugin_blog_categories/tests/south_settings.py
cmsplugin_blog_categories/tests/tags_tests.py
cmsplugin_blog_categories/tests/test_settings.py
cmsplugin_blog_categories/tests/urls.py
cmsplugin_blog_categories/tests/integration_tests/views_tests.py
cmsplugin_blog_categories/tests/test_app/__init__.py
cmsplugin_blog_categories/tests/test_app/models.py
