Metadata-Version: 1.0
Name: cmsplugin-blog-categories
Version: 0.7
Summary: Extension for cmsplugin-blog which adds categories to the blog.
